XStatic_asciinema_player-2.6.1.1-py3.13-nspkg.pth
xstatic/pkg/asciinema_player/__init__.py
xstatic/pkg/asciinema_player/data/asciinema-player.css
xstatic/pkg/asciinema_player/data/asciinema-player.js
xstatic_asciinema_player-2.6.1.1.dist-info/METADATA
xstatic_asciinema_player-2.6.1.1.dist-info/WHEEL
xstatic_asciinema_player-2.6.1.1.dist-info/namespace_packages.txt
xstatic_asciinema_player-2.6.1.1.dist-info/top_level.txt
xstatic_asciinema_player-2.6.1.1.dist-info/RECORD
