Metadata-Version: 2.4
Name: XStatic-asciinema-player
Version: 2.6.1.1
Summary: asciinema-player 2.6.1 (XStatic packaging standard)
Home-page: https://github.com/asciinema/asciinema-player
Maintainer: Thomas Waldmann
Maintainer-email: tw@waldmann-edv.de
License: (same as asciinema-player)
Keywords: asciinema_player xstatic
Platform: any
Dynamic: description
Dynamic: home-page
Dynamic: keywords
Dynamic: license
Dynamic: maintainer
Dynamic: maintainer-email
Dynamic: platform
Dynamic: summary
